{
  "_format": "hh-sol-cache-2",
  "files": {
    "C:\\Users\\cam20\\OneDrive\\Documents\\Unicorn Factory\\ngeth\\e2e\\explorer\\hardhat\\src\\BaseERC1155.sol": {
      "lastModificationDate": 1655304119053,
      "contentHash": "2da0657b16d38cff86776bf8aa00de4a",
      "sourceName": "src/BaseERC1155.sol",
      "solcConfig": {
        "version": "0.8.11",
        "settings": {
          "optimizer": {
            "enabled": false,
            "runs": 200
          },
          "outputSelection": {
            "*": {
              "*": [
                "abi",
                "evm.bytecode",
                "evm.deployedBytecode",
                "evm.methodIdentifiers",
                "metadata"
              ],
              "": [
                "ast"
              ]
            }
          }
        }
      },
      "imports": [
        "@openzeppelin/contracts/token/ERC1155/ERC1155.sol",
        "@openzeppelin/contracts/access/Ownable.sol"
      ],
      "versionPragmas": [
        "^0.8.11"
      ],
      "artifacts": [
        "BaseERC1155"
      ]
    },
    "C:\\Users\\cam20\\OneDrive\\Documents\\Unicorn Factory\\ngeth\\node_modules\\@openzeppelin\\contracts\\token\\ERC1155\\ERC1155.sol": {
      "lastModificationDate": 1655809183182,
      "contentHash": "1d68a32647e54f6acd6ff471d940ef4c",
      "sourceName": "@openzeppelin/contracts/token/ERC1155/ERC1155.sol",
      "solcConfig": {
        "version": "0.8.11",
        "settings": {
          "optimizer": {
            "enabled": false,
            "runs": 200
          },
          "outputSelection": {
            "*": {
              "*": [
                "abi",
                "evm.bytecode",
                "evm.deployedBytecode",
                "evm.methodIdentifiers",
                "metadata"
              ],
              "": [
                "ast"
              ]
            }
          }
        }
      },
      "imports": [
        "./IERC1155.sol",
        "./IERC1155Receiver.sol",
        "./extensions/IERC1155MetadataURI.sol",
        "../../utils/Address.sol",
        "../../utils/Context.sol",
        "../../utils/introspection/ERC165.sol"
      ],
      "versionPragmas": [
        "^0.8.0"
      ],
      "artifacts": [
        "ERC1155"
      ]
    },
    "C:\\Users\\cam20\\OneDrive\\Documents\\Unicorn Factory\\ngeth\\node_modules\\@openzeppelin\\contracts\\access\\Ownable.sol": {
      "lastModificationDate": 1655809188236,
      "contentHash": "8398972af73b4e9e5ff3b31cad86234f",
      "sourceName": "@openzeppelin/contracts/access/Ownable.sol",
      "solcConfig": {
        "version": "0.8.11",
        "settings": {
          "optimizer": {
            "enabled": false,
            "runs": 200
          },
          "outputSelection": {
            "*": {
              "*": [
                "abi",
                "evm.bytecode",
                "evm.deployedBytecode",
                "evm.methodIdentifiers",
                "metadata"
              ],
              "": [
                "ast"
              ]
            }
          }
        }
      },
      "imports": [
        "../utils/Context.sol"
      ],
      "versionPragmas": [
        "^0.8.0"
      ],
      "artifacts": [
        "Ownable"
      ]
    },
    "C:\\Users\\cam20\\OneDrive\\Documents\\Unicorn Factory\\ngeth\\node_modules\\@openzeppelin\\contracts\\token\\ERC1155\\IERC1155.sol": {
      "lastModificationDate": 1655809185947,
      "contentHash": "59e1bc5713fdebc7f821dc52f4d3e0ef",
      "sourceName": "@openzeppelin/contracts/token/ERC1155/IERC1155.sol",
      "solcConfig": {
        "version": "0.8.11",
        "settings": {
          "optimizer": {
            "enabled": false,
            "runs": 200
          },
          "outputSelection": {
            "*": {
              "*": [
                "abi",
                "evm.bytecode",
                "evm.deployedBytecode",
                "evm.methodIdentifiers",
                "metadata"
              ],
              "": [
                "ast"
              ]
            }
          }
        }
      },
      "imports": [
        "../../utils/introspection/IERC165.sol"
      ],
      "versionPragmas": [
        "^0.8.0"
      ],
      "artifacts": [
        "IERC1155"
      ]
    },
    "C:\\Users\\cam20\\OneDrive\\Documents\\Unicorn Factory\\ngeth\\node_modules\\@openzeppelin\\contracts\\token\\ERC1155\\IERC1155Receiver.sol": {
      "lastModificationDate": 1655809186105,
      "contentHash": "90eddd06deda7317b4441f04ec26db4d",
      "sourceName": "@openzeppelin/contracts/token/ERC1155/IERC1155Receiver.sol",
      "solcConfig": {
        "version": "0.8.11",
        "settings": {
          "optimizer": {
            "enabled": false,
            "runs": 200
          },
          "outputSelection": {
            "*": {
              "*": [
                "abi",
                "evm.bytecode",
                "evm.deployedBytecode",
                "evm.methodIdentifiers",
                "metadata"
              ],
              "": [
                "ast"
              ]
            }
          }
        }
      },
      "imports": [
        "../../utils/introspection/IERC165.sol"
      ],
      "versionPragmas": [
        "^0.8.0"
      ],
      "artifacts": [
        "IERC1155Receiver"
      ]
    },
    "C:\\Users\\cam20\\OneDrive\\Documents\\Unicorn Factory\\ngeth\\node_modules\\@openzeppelin\\contracts\\token\\ERC1155\\extensions\\IERC1155MetadataURI.sol": {
      "lastModificationDate": 1655809186029,
      "contentHash": "9148c2e10c4efb12c71a7f080da5559b",
      "sourceName": "@openzeppelin/contracts/token/ERC1155/extensions/IERC1155MetadataURI.sol",
      "solcConfig": {
        "version": "0.8.11",
        "settings": {
          "optimizer": {
            "enabled": false,
            "runs": 200
          },
          "outputSelection": {
            "*": {
              "*": [
                "abi",
                "evm.bytecode",
                "evm.deployedBytecode",
                "evm.methodIdentifiers",
                "metadata"
              ],
              "": [
                "ast"
              ]
            }
          }
        }
      },
      "imports": [
        "../IERC1155.sol"
      ],
      "versionPragmas": [
        "^0.8.0"
      ],
      "artifacts": [
        "IERC1155MetadataURI"
      ]
    },
    "C:\\Users\\cam20\\OneDrive\\Documents\\Unicorn Factory\\ngeth\\node_modules\\@openzeppelin\\contracts\\utils\\Address.sol": {
      "lastModificationDate": 1655809182012,
      "contentHash": "4cff8b2ea0d958750786b4e3ca308445",
      "sourceName": "@openzeppelin/contracts/utils/Address.sol",
      "solcConfig": {
        "version": "0.8.11",
        "settings": {
          "optimizer": {
            "enabled": false,
            "runs": 200
          },
          "outputSelection": {
            "*": {
              "*": [
                "abi",
                "evm.bytecode",
                "evm.deployedBytecode",
                "evm.methodIdentifiers",
                "metadata"
              ],
              "": [
                "ast"
              ]
            }
          }
        }
      },
      "imports": [],
      "versionPragmas": [
        "^0.8.0"
      ],
      "artifacts": [
        "Address"
      ]
    },
    "C:\\Users\\cam20\\OneDrive\\Documents\\Unicorn Factory\\ngeth\\node_modules\\@openzeppelin\\contracts\\utils\\Context.sol": {
      "lastModificationDate": 1655809182496,
      "contentHash": "5f2c5c4b6af2dd4551027144797bc8be",
      "sourceName": "@openzeppelin/contracts/utils/Context.sol",
      "solcConfig": {
        "version": "0.8.11",
        "settings": {
          "optimizer": {
            "enabled": false,
            "runs": 200
          },
          "outputSelection": {
            "*": {
              "*": [
                "abi",
                "evm.bytecode",
                "evm.deployedBytecode",
                "evm.methodIdentifiers",
                "metadata"
              ],
              "": [
                "ast"
              ]
            }
          }
        }
      },
      "imports": [],
      "versionPragmas": [
        "^0.8.0"
      ],
      "artifacts": [
        "Context"
      ]
    },
    "C:\\Users\\cam20\\OneDrive\\Documents\\Unicorn Factory\\ngeth\\node_modules\\@openzeppelin\\contracts\\utils\\introspection\\ERC165.sol": {
      "lastModificationDate": 1655809183621,
      "contentHash": "0e7db055ce108f9da7bb6686a00287c0",
      "sourceName": "@openzeppelin/contracts/utils/introspection/ERC165.sol",
      "solcConfig": {
        "version": "0.8.11",
        "settings": {
          "optimizer": {
            "enabled": false,
            "runs": 200
          },
          "outputSelection": {
            "*": {
              "*": [
                "abi",
                "evm.bytecode",
                "evm.deployedBytecode",
                "evm.methodIdentifiers",
                "metadata"
              ],
              "": [
                "ast"
              ]
            }
          }
        }
      },
      "imports": [
        "./IERC165.sol"
      ],
      "versionPragmas": [
        "^0.8.0"
      ],
      "artifacts": [
        "ERC165"
      ]
    },
    "C:\\Users\\cam20\\OneDrive\\Documents\\Unicorn Factory\\ngeth\\node_modules\\@openzeppelin\\contracts\\utils\\introspection\\IERC165.sol": {
      "lastModificationDate": 1655809186364,
      "contentHash": "03e6768535ac4da0e9756f1d8a4a018a",
      "sourceName": "@openzeppelin/contracts/utils/introspection/IERC165.sol",
      "solcConfig": {
        "version": "0.8.11",
        "settings": {
          "optimizer": {
            "enabled": false,
            "runs": 200
          },
          "outputSelection": {
            "*": {
              "*": [
                "abi",
                "evm.bytecode",
                "evm.deployedBytecode",
                "evm.methodIdentifiers",
                "metadata"
              ],
              "": [
                "ast"
              ]
            }
          }
        }
      },
      "imports": [],
      "versionPragmas": [
        "^0.8.0"
      ],
      "artifacts": [
        "IERC165"
      ]
    },
    "C:\\Users\\cam20\\OneDrive\\Documents\\Unicorn Factory\\ngeth\\node_modules\\@openzeppelin\\contracts\\token\\ERC20\\ERC20.sol": {
      "lastModificationDate": 1655809183936,
      "contentHash": "f48de0eaae9544072b8766e2eac528a7",
      "sourceName": "@openzeppelin/contracts/token/ERC20/ERC20.sol",
      "solcConfig": {
        "version": "0.8.11",
        "settings": {
          "optimizer": {
            "enabled": false,
            "runs": 200
          },
          "outputSelection": {
            "*": {
              "*": [
                "abi",
                "evm.bytecode",
                "evm.deployedBytecode",
                "evm.methodIdentifiers",
                "metadata"
              ],
              "": [
                "ast"
              ]
            }
          }
        }
      },
      "imports": [
        "./IERC20.sol",
        "./extensions/IERC20Metadata.sol",
        "../../utils/Context.sol"
      ],
      "versionPragmas": [
        "^0.8.0"
      ],
      "artifacts": [
        "ERC20"
      ]
    },
    "C:\\Users\\cam20\\OneDrive\\Documents\\Unicorn Factory\\ngeth\\node_modules\\@openzeppelin\\contracts\\token\\ERC20\\IERC20.sol": {
      "lastModificationDate": 1655809186584,
      "contentHash": "302d9755e46bc69d7058b0cbe7185e37",
      "sourceName": "@openzeppelin/contracts/token/ERC20/IERC20.sol",
      "solcConfig": {
        "version": "0.8.11",
        "settings": {
          "optimizer": {
            "enabled": false,
            "runs": 200
          },
          "outputSelection": {
            "*": {
              "*": [
                "abi",
                "evm.bytecode",
                "evm.deployedBytecode",
                "evm.methodIdentifiers",
                "metadata"
              ],
              "": [
                "ast"
              ]
            }
          }
        }
      },
      "imports": [],
      "versionPragmas": [
        "^0.8.0"
      ],
      "artifacts": [
        "IERC20"
      ]
    },
    "C:\\Users\\cam20\\OneDrive\\Documents\\Unicorn Factory\\ngeth\\node_modules\\@openzeppelin\\contracts\\token\\ERC20\\extensions\\IERC20Metadata.sol": {
      "lastModificationDate": 1655809186661,
      "contentHash": "909ab67fc5c25033fe6cd364f8c056f9",
      "sourceName": "@openzeppelin/contracts/token/ERC20/extensions/IERC20Metadata.sol",
      "solcConfig": {
        "version": "0.8.11",
        "settings": {
          "optimizer": {
            "enabled": false,
            "runs": 200
          },
          "outputSelection": {
            "*": {
              "*": [
                "abi",
                "evm.bytecode",
                "evm.deployedBytecode",
                "evm.methodIdentifiers",
                "metadata"
              ],
              "": [
                "ast"
              ]
            }
          }
        }
      },
      "imports": [
        "../IERC20.sol"
      ],
      "versionPragmas": [
        "^0.8.0"
      ],
      "artifacts": [
        "IERC20Metadata"
      ]
    },
    "C:\\Users\\cam20\\OneDrive\\Documents\\Unicorn Factory\\ngeth\\e2e\\explorer\\hardhat\\src\\BaseERC20.sol": {
      "lastModificationDate": 1654685152899,
      "contentHash": "7b5044f04ed5b49b310cc4da98ef71e9",
      "sourceName": "src/BaseERC20.sol",
      "solcConfig": {
        "version": "0.8.11",
        "settings": {
          "optimizer": {
            "enabled": false,
            "runs": 200
          },
          "outputSelection": {
            "*": {
              "*": [
                "abi",
                "evm.bytecode",
                "evm.deployedBytecode",
                "evm.methodIdentifiers",
                "metadata"
              ],
              "": [
                "ast"
              ]
            }
          }
        }
      },
      "imports": [
        "@openzeppelin/contracts/token/ERC20/ERC20.sol"
      ],
      "versionPragmas": [
        "^0.8.11"
      ],
      "artifacts": [
        "BaseERC20"
      ]
    },
    "C:\\Users\\cam20\\OneDrive\\Documents\\Unicorn Factory\\ngeth\\e2e\\explorer\\hardhat\\src\\ERC1155Proxy.sol": {
      "lastModificationDate": 1655741186353,
      "contentHash": "676abdd4c490d57f36d2f91bbc30a312",
      "sourceName": "src/ERC1155Proxy.sol",
      "solcConfig": {
        "version": "0.8.11",
        "settings": {
          "optimizer": {
            "enabled": false,
            "runs": 200
          },
          "outputSelection": {
            "*": {
              "*": [
                "abi",
                "evm.bytecode",
                "evm.deployedBytecode",
                "evm.methodIdentifiers",
                "metadata"
              ],
              "": [
                "ast"
              ]
            }
          }
        }
      },
      "imports": [
        "./UpgradeableERC1155.sol",
        "@openzeppelin/contracts/proxy/Clones.sol"
      ],
      "versionPragmas": [
        "^0.8.11"
      ],
      "artifacts": [
        "ERC1155Proxy"
      ]
    },
    "C:\\Users\\cam20\\OneDrive\\Documents\\Unicorn Factory\\ngeth\\e2e\\explorer\\hardhat\\src\\UpgradeableERC1155.sol": {
      "lastModificationDate": 1655741186353,
      "contentHash": "51d45f40bbaa440e9aec817a33474f55",
      "sourceName": "src/UpgradeableERC1155.sol",
      "solcConfig": {
        "version": "0.8.11",
        "settings": {
          "optimizer": {
            "enabled": false,
            "runs": 200
          },
          "outputSelection": {
            "*": {
              "*": [
                "abi",
                "evm.bytecode",
                "evm.deployedBytecode",
                "evm.methodIdentifiers",
                "metadata"
              ],
              "": [
                "ast"
              ]
            }
          }
        }
      },
      "imports": [
        "@openzeppelin/contracts-upgradeable/token/ERC1155/ERC1155Upgradeable.sol",
        "@openzeppelin/contracts-upgradeable/access/OwnableUpgradeable.sol"
      ],
      "versionPragmas": [
        "^0.8.11"
      ],
      "artifacts": [
        "UpgradeableERC1155"
      ]
    },
    "C:\\Users\\cam20\\OneDrive\\Documents\\Unicorn Factory\\ngeth\\node_modules\\@openzeppelin\\contracts\\proxy\\Clones.sol": {
      "lastModificationDate": 1655809182379,
      "contentHash": "f741efede98f234458f02f818f80c7f3",
      "sourceName": "@openzeppelin/contracts/proxy/Clones.sol",
      "solcConfig": {
        "version": "0.8.11",
        "settings": {
          "optimizer": {
            "enabled": false,
            "runs": 200
          },
          "outputSelection": {
            "*": {
              "*": [
                "abi",
                "evm.bytecode",
                "evm.deployedBytecode",
                "evm.methodIdentifiers",
                "metadata"
              ],
              "": [
                "ast"
              ]
            }
          }
        }
      },
      "imports": [],
      "versionPragmas": [
        "^0.8.0"
      ],
      "artifacts": [
        "Clones"
      ]
    },
    "C:\\Users\\cam20\\OneDrive\\Documents\\Unicorn Factory\\ngeth\\node_modules\\@openzeppelin\\contracts-upgradeable\\token\\ERC1155\\ERC1155Upgradeable.sol": {
      "lastModificationDate": 1655809183907,
      "contentHash": "b8451cd97ec3d3dda466157b83bf38b7",
      "sourceName": "@openzeppelin/contracts-upgradeable/token/ERC1155/ERC1155Upgradeable.sol",
      "solcConfig": {
        "version": "0.8.11",
        "settings": {
          "optimizer": {
            "enabled": false,
            "runs": 200
          },
          "outputSelection": {
            "*": {
              "*": [
                "abi",
                "evm.bytecode",
                "evm.deployedBytecode",
                "evm.methodIdentifiers",
                "metadata"
              ],
              "": [
                "ast"
              ]
            }
          }
        }
      },
      "imports": [
        "./IERC1155Upgradeable.sol",
        "./IERC1155ReceiverUpgradeable.sol",
        "./extensions/IERC1155MetadataURIUpgradeable.sol",
        "../../utils/AddressUpgradeable.sol",
        "../../utils/ContextUpgradeable.sol",
        "../../utils/introspection/ERC165Upgradeable.sol",
        "../../proxy/utils/Initializable.sol"
      ],
      "versionPragmas": [
        "^0.8.0"
      ],
      "artifacts": [
        "ERC1155Upgradeable"
      ]
    },
    "C:\\Users\\cam20\\OneDrive\\Documents\\Unicorn Factory\\ngeth\\node_modules\\@openzeppelin\\contracts-upgradeable\\access\\OwnableUpgradeable.sol": {
      "lastModificationDate": 1655809189099,
      "contentHash": "11b77de3cb69dfc6b342ec87bd09cbdd",
      "sourceName": "@openzeppelin/contracts-upgradeable/access/OwnableUpgradeable.sol",
      "solcConfig": {
        "version": "0.8.11",
        "settings": {
          "optimizer": {
            "enabled": false,
            "runs": 200
          },
          "outputSelection": {
            "*": {
              "*": [
                "abi",
                "evm.bytecode",
                "evm.deployedBytecode",
                "evm.methodIdentifiers",
                "metadata"
              ],
              "": [
                "ast"
              ]
            }
          }
        }
      },
      "imports": [
        "../utils/ContextUpgradeable.sol",
        "../proxy/utils/Initializable.sol"
      ],
      "versionPragmas": [
        "^0.8.0"
      ],
      "artifacts": [
        "OwnableUpgradeable"
      ]
    },
    "C:\\Users\\cam20\\OneDrive\\Documents\\Unicorn Factory\\ngeth\\node_modules\\@openzeppelin\\contracts-upgradeable\\token\\ERC1155\\IERC1155Upgradeable.sol": {
      "lastModificationDate": 1655809186664,
      "contentHash": "a51bc173c3333372b3aa9913bc21f38c",
      "sourceName": "@openzeppelin/contracts-upgradeable/token/ERC1155/IERC1155Upgradeable.sol",
      "solcConfig": {
        "version": "0.8.11",
        "settings": {
          "optimizer": {
            "enabled": false,
            "runs": 200
          },
          "outputSelection": {
            "*": {
              "*": [
                "abi",
                "evm.bytecode",
                "evm.deployedBytecode",
                "evm.methodIdentifiers",
                "metadata"
              ],
              "": [
                "ast"
              ]
            }
          }
        }
      },
      "imports": [
        "../../utils/introspection/IERC165Upgradeable.sol"
      ],
      "versionPragmas": [
        "^0.8.0"
      ],
      "artifacts": [
        "IERC1155Upgradeable"
      ]
    },
    "C:\\Users\\cam20\\OneDrive\\Documents\\Unicorn Factory\\ngeth\\node_modules\\@openzeppelin\\contracts-upgradeable\\token\\ERC1155\\IERC1155ReceiverUpgradeable.sol": {
      "lastModificationDate": 1655809186588,
      "contentHash": "eb51ed084f6f7fd2c7098715c5690285",
      "sourceName": "@openzeppelin/contracts-upgradeable/token/ERC1155/IERC1155ReceiverUpgradeable.sol",
      "solcConfig": {
        "version": "0.8.11",
        "settings": {
          "optimizer": {
            "enabled": false,
            "runs": 200
          },
          "outputSelection": {
            "*": {
              "*": [
                "abi",
                "evm.bytecode",
                "evm.deployedBytecode",
                "evm.methodIdentifiers",
                "metadata"
              ],
              "": [
                "ast"
              ]
            }
          }
        }
      },
      "imports": [
        "../../utils/introspection/IERC165Upgradeable.sol"
      ],
      "versionPragmas": [
        "^0.8.0"
      ],
      "artifacts": [
        "IERC1155ReceiverUpgradeable"
      ]
    },
    "C:\\Users\\cam20\\OneDrive\\Documents\\Unicorn Factory\\ngeth\\node_modules\\@openzeppelin\\contracts-upgradeable\\token\\ERC1155\\extensions\\IERC1155MetadataURIUpgradeable.sol": {
      "lastModificationDate": 1655809186512,
      "contentHash": "8b7e95c747e2dab3b5444b37410a8315",
      "sourceName": "@openzeppelin/contracts-upgradeable/token/ERC1155/extensions/IERC1155MetadataURIUpgradeable.sol",
      "solcConfig": {
        "version": "0.8.11",
        "settings": {
          "optimizer": {
            "enabled": false,
            "runs": 200
          },
          "outputSelection": {
            "*": {
              "*": [
                "abi",
                "evm.bytecode",
                "evm.deployedBytecode",
                "evm.methodIdentifiers",
                "metadata"
              ],
              "": [
                "ast"
              ]
            }
          }
        }
      },
      "imports": [
        "../IERC1155Upgradeable.sol"
      ],
      "versionPragmas": [
        "^0.8.0"
      ],
      "artifacts": [
        "IERC1155MetadataURIUpgradeable"
      ]
    },
    "C:\\Users\\cam20\\OneDrive\\Documents\\Unicorn Factory\\ngeth\\node_modules\\@openzeppelin\\contracts-upgradeable\\utils\\AddressUpgradeable.sol": {
      "lastModificationDate": 1655809182293,
      "contentHash": "b70d2e0552ab1f44f7e44b5f8379c358",
      "sourceName": "@openzeppelin/contracts-upgradeable/utils/AddressUpgradeable.sol",
      "solcConfig": {
        "version": "0.8.11",
        "settings": {
          "optimizer": {
            "enabled": false,
            "runs": 200
          },
          "outputSelection": {
            "*": {
              "*": [
                "abi",
                "evm.bytecode",
                "evm.deployedBytecode",
                "evm.methodIdentifiers",
                "metadata"
              ],
              "": [
                "ast"
              ]
            }
          }
        }
      },
      "imports": [],
      "versionPragmas": [
        "^0.8.1"
      ],
      "artifacts": [
        "AddressUpgradeable"
      ]
    },
    "C:\\Users\\cam20\\OneDrive\\Documents\\Unicorn Factory\\ngeth\\node_modules\\@openzeppelin\\contracts-upgradeable\\utils\\ContextUpgradeable.sol": {
      "lastModificationDate": 1655809182679,
      "contentHash": "6200b84950eb05b4a92a39fd1d6e0f9b",
      "sourceName": "@openzeppelin/contracts-upgradeable/utils/ContextUpgradeable.sol",
      "solcConfig": {
        "version": "0.8.11",
        "settings": {
          "optimizer": {
            "enabled": false,
            "runs": 200
          },
          "outputSelection": {
            "*": {
              "*": [
                "abi",
                "evm.bytecode",
                "evm.deployedBytecode",
                "evm.methodIdentifiers",
                "metadata"
              ],
              "": [
                "ast"
              ]
            }
          }
        }
      },
      "imports": [
        "../proxy/utils/Initializable.sol"
      ],
      "versionPragmas": [
        "^0.8.0"
      ],
      "artifacts": [
        "ContextUpgradeable"
      ]
    },
    "C:\\Users\\cam20\\OneDrive\\Documents\\Unicorn Factory\\ngeth\\node_modules\\@openzeppelin\\contracts-upgradeable\\utils\\introspection\\ERC165Upgradeable.sol": {
      "lastModificationDate": 1655809184033,
      "contentHash": "5f2d8b81c0ff5bd2047b4846c20b998d",
      "sourceName": "@openzeppelin/contracts-upgradeable/utils/introspection/ERC165Upgradeable.sol",
      "solcConfig": {
        "version": "0.8.11",
        "settings": {
          "optimizer": {
            "enabled": false,
            "runs": 200
          },
          "outputSelection": {
            "*": {
              "*": [
                "abi",
                "evm.bytecode",
                "evm.deployedBytecode",
                "evm.methodIdentifiers",
                "metadata"
              ],
              "": [
                "ast"
              ]
            }
          }
        }
      },
      "imports": [
        "./IERC165Upgradeable.sol",
        "../../proxy/utils/Initializable.sol"
      ],
      "versionPragmas": [
        "^0.8.0"
      ],
      "artifacts": [
        "ERC165Upgradeable"
      ]
    },
    "C:\\Users\\cam20\\OneDrive\\Documents\\Unicorn Factory\\ngeth\\node_modules\\@openzeppelin\\contracts-upgradeable\\proxy\\utils\\Initializable.sol": {
      "lastModificationDate": 1655809188702,
      "contentHash": "49c8ad51a559f6dda13d35874f7dfdb9",
      "sourceName": "@openzeppelin/contracts-upgradeable/proxy/utils/Initializable.sol",
      "solcConfig": {
        "version": "0.8.11",
        "settings": {
          "optimizer": {
            "enabled": false,
            "runs": 200
          },
          "outputSelection": {
            "*": {
              "*": [
                "abi",
                "evm.bytecode",
                "evm.deployedBytecode",
                "evm.methodIdentifiers",
                "metadata"
              ],
              "": [
                "ast"
              ]
            }
          }
        }
      },
      "imports": [
        "../../utils/AddressUpgradeable.sol"
      ],
      "versionPragmas": [
        "^0.8.0"
      ],
      "artifacts": [
        "Initializable"
      ]
    },
    "C:\\Users\\cam20\\OneDrive\\Documents\\Unicorn Factory\\ngeth\\node_modules\\@openzeppelin\\contracts-upgradeable\\utils\\introspection\\IERC165Upgradeable.sol": {
      "lastModificationDate": 1655809186923,
      "contentHash": "d6ecf203a5e72c845be9bbf2f304a289",
      "sourceName": "@openzeppelin/contracts-upgradeable/utils/introspection/IERC165Upgradeable.sol",
      "solcConfig": {
        "version": "0.8.11",
        "settings": {
          "optimizer": {
            "enabled": false,
            "runs": 200
          },
          "outputSelection": {
            "*": {
              "*": [
                "abi",
                "evm.bytecode",
                "evm.deployedBytecode",
                "evm.methodIdentifiers",
                "metadata"
              ],
              "": [
                "ast"
              ]
            }
          }
        }
      },
      "imports": [],
      "versionPragmas": [
        "^0.8.0"
      ],
      "artifacts": [
        "IERC165Upgradeable"
      ]
    }
  }
}
