{
  "$schema": "http://json-schema.org/schema",
  "title": "Serve Node",
  "description": "Serve an Ethereum node and deploy contracts defined by autoDeploy.",
  "type": "object",
  "properties": {
    "tsconfig": {
      "type": "string",
      "description": "The path to the tsconfig file used to run hardhat."
    },
    "config": {
      "type": "string",
      "description": "The path to the hardhat configuration file."
    }
  },
  "additionalProperties": false,
  "required": ["tsconfig", "config"]
}
